[
    {
        "index":"1",
        "name":"小丸子",
        "idNo":"321321*******1101",
        "iphoneNo":"18762107673"
    },{
        "index":"2",
        "name":"小丸子",
        "idNo":"321321*******1101",
        "iphoneNo":"18762107673"
    },{
        "index":"3",
        "name":"小丸子",
        "idNo":"321321*******1101",
        "iphoneNo":"18762107673"
    },{
        "index":"4",
        "name":"小丸子",
        "idNo":"321321*******1101",
        "iphoneNo":"18762107673"
    },{
        "index":"5",
        "name":"小丸子",
        "idNo":"321321*******1101",
        "iphoneNo":"18762107673"
    },{
        "index":"6",
        "name":"小丸子",
        "idNo":"321321*******1101",
        "iphoneNo":"18762107673"
    },{
        "index":"7",
        "name":"小丸子",
        "idNo":"321321*******1101",
        "iphoneNo":"18762107673"
    },
    {
        "index":"8",
        "name":"小丸子",
        "idNo":"321321*******1101",
        "iphoneNo":"18762107673"
    },{
        "index":"9",
        "name":"小丸子",
        "idNo":"321321*******1101",
        "iphoneNo":"18762107673"
    },{
        "index":"10",
        "name":"小丸子",
        "idNo":"321321*******1101",
        "iphoneNo":"18762107673"
    },{
        "index":"11",
        "name":"小丸子",
        "idNo":"321321*******1101",
        "iphoneNo":"18762107673"
    },{
        "index":"12",
        "name":"小丸子",
        "idNo":"321321*******1101",
        "iphoneNo":"18762107673"
    },{
        "index":"13",
        "name":"小丸子",
        "idNo":"321321*******1101",
        "iphoneNo":"18762107673"
    },{
        "index":"14",
        "name":"小丸子",
        "idNo":"321321*******1101",
        "iphoneNo":"18762107673"
    }
]